datedelta.py
datedelta-1.3.dist-info/LICENSE
datedelta-1.3.dist-info/METADATA
datedelta-1.3.dist-info/WHEEL
datedelta-1.3.dist-info/pbr.json
datedelta-1.3.dist-info/top_level.txt
datedelta-1.3.dist-info/RECORD
