Metadata-Version: 1.1
Name: datedelta
Version: 1.3
Summary: Like datetime.timedelta, for date arithmetic.
Home-page: https://github.com/aaugustin/datedelta
Author: Aymeric Augustin
Author-email: aymeric.augustin@m4x.org
License: BSD
Platform: UNKNOWN
Classifier: Development Status :: 5 - Production/Stable
Classifier: Intended Audience :: Developers
Classifier: License :: OSI Approved :: BSD License
Classifier: Operating System :: OS Independent
Classifier: Programming Language :: Python
Classifier: Programming Language :: Python :: 3
Classifier: Programming Language :: Python :: 3.4
Classifier: Programming Language :: Python :: 3.5
Classifier: Programming Language :: Python :: 3.6
Classifier: Programming Language :: Python :: 3.7
